calibcamlib/__init__.py
calibcamlib/board.py
calibcamlib/camera.py
calibcamlib/camerasystem.py
calibcamlib/detection.py
calibcamlib/dist_MaEtAl2003_model0.py
calibcamlib/dist_MaEtAl2003_model3.py
calibcamlib/dist_OpenCV.py
calibcamlib/helper.py
calibcamlib/yaml_helper.py
bbo_calibcamlib-0.3.17.dist-info/METADATA
bbo_calibcamlib-0.3.17.dist-info/WHEEL
bbo_calibcamlib-0.3.17.dist-info/licenses/LICENSE
bbo_calibcamlib-0.3.17.dist-info/RECORD
