Metadata-Version: 2.3
Name: bbo-calibcamlib
Version: 0.3.17
Summary: Library to work with calibration from bbo-calibcam
Project-URL: Homepage, https://github.com/bbo-lab/calibcamlib
Author-email: "BBO-lab @ caesar" <kay-michael.voit@caesar.de>
License: BSD-3-Clause
Classifier: License :: OSI Approved :: BSD License
Classifier: Programming Language :: Python :: 3
Classifier: Programming Language :: Python :: 3.6
Classifier: Programming Language :: Python :: 3.7
Classifier: Programming Language :: Python :: 3.8
Classifier: Programming Language :: Python :: 3.9
Requires-Dist: numpy
Requires-Dist: pyyaml
Requires-Dist: scipy
